{"success":true,"data":{"charts":[],"title":"Dane pomiarowe dla parametru Py\u0142 zawieszony PM10 w dniu 12.01.2017 r.","unitLabel":"&micro;g\/m<sup>3<\/sup>","series":[{"label":"Aleja Krasi\u0144skiego","measType":"auto","paramLabel":"Py\u0142 zawieszony PM10","paramId":"pm10","paramCode":"PM10","paramPostfix":"","aggType":"A1h","ord":7,"interval":3600,"count":24,"retroCount":2,"startTime":1484179200,"extStartTime":1484172000,"coverageRate":0.75,"isAvgValid":true,"thresholds":{"at":null,"it":null,"tv":null,"lv":null,"atDecimals":0,"itDecimals":0,"tvDecimals":0,"lvDecimals":0},"data":[["1484172000","276.895"],["1484175600","285.27"],["1484179200","290.87"],["1484182800","165.238"],["1484186400","26.4842"],["1484190000","24.4122"],["1484193600","20.4476"],["1484197200","27.7911"],["1484200800","34.437"],["1484204400","38.3103"],["1484208000","37.5743"],["1484211600","35.8154"],["1484215200","38.4955"],["1484218800","37.0695"],["1484222400","42.5327"],["1484226000","33.2731"],["1484229600","28.2367"],["1484233200","32.0472"],["1484236800","34.519"],["1484240400","42.4295"],["1484244000","60.9584"],["1484247600","68.5873"],["1484251200","58.3249"],["1484254800","65.225"],["1484258400","53.1036"],["1484262000","37.3721"]],"avg":{"avg":"55.5648","min":"20.4476","max":"290.87"},"thresholdsForAvg":{"avg":{"at":300,"it":200,"tv":null,"lv":50,"atDecimals":0,"itDecimals":0,"tvDecimals":0,"lvDecimals":0},"min":null,"max":null},"decimals":0,"unit":"ug\/m3","unitLabel":"&micro;g\/m<sup>3<\/sup>","scaleMin":null,"scaleMax":null,"chartTooltipContent":"%y.# %ly o godz. %x"},{"label":"Krak\u00f3w, os. Piast\u00f3w","measType":"auto","paramLabel":"Py\u0142 zawieszony PM10","paramId":"pm10","paramCode":"PM10","paramPostfix":"","aggType":"A1h","ord":7,"interval":3600,"count":24,"retroCount":2,"startTime":1484179200,"extStartTime":1484172000,"coverageRate":0.75,"isAvgValid":true,"thresholds":{"at":null,"it":null,"tv":null,"lv":null,"atDecimals":0,"itDecimals":0,"tvDecimals":0,"lvDecimals":0},"data":[["1484172000","258.483"],["1484175600","232.003"],["1484179200","152.238"],["1484182800","90.4634"],["1484186400","29.5444"],["1484190000","20.0186"],["1484193600","17.7514"],["1484197200","18.1958"],["1484200800","22.3327"],["1484204400","22.9557"],["1484208000","31.836"],["1484211600","29.8033"],["1484215200","30.5028"],["1484218800","30.9189"],["1484222400","32.1127"],["1484226000","29.6985"],["1484229600","21.2919"],["1484233200","20.9518"],["1484236800","23.1552"],["1484240400","26.1589"],["1484244000","29.9328"],["1484247600","47.0836"],["1484251200","46.4269"],["1484254800","40.5211"],["1484258400","32.1509"],["1484262000","22.9516"]],"avg":{"avg":"36.2082","min":"17.7514","max":"152.238"},"thresholdsForAvg":{"avg":{"at":300,"it":200,"tv":null,"lv":50,"atDecimals":0,"itDecimals":0,"tvDecimals":0,"lvDecimals":0},"min":null,"max":null},"decimals":0,"unit":"ug\/m3","unitLabel":"&micro;g\/m<sup>3<\/sup>","scaleMin":null,"scaleMax":null,"chartTooltipContent":"%y.# %ly o godz. %x"},{"label":"Krak\u00f3w, os. Wad\u00f3w","measType":"auto","paramLabel":"Py\u0142 zawieszony PM10","paramId":"pm10","paramCode":"PM10","paramPostfix":"","aggType":"A1h","ord":7,"interval":3600,"count":24,"retroCount":2,"startTime":1484179200,"extStartTime":1484172000,"coverageRate":0.75,"isAvgValid":true,"thresholds":{"at":null,"it":null,"tv":null,"lv":null,"atDecimals":0,"itDecimals":0,"tvDecimals":0,"lvDecimals":0},"data":[["1484172000","229.797"],["1484175600","138.288"],["1484179200","68.0156"],["1484182800","114.003"],["1484186400","47.1564"],["1484190000","23.9539"],["1484193600","27.0419"],["1484197200","23.5204"],["1484200800","29.8455"],["1484204400","34.2826"],["1484208000","31.8611"],["1484211600","30.6403"],["1484215200","34.7348"],["1484218800","30.1593"],["1484222400","29.1087"],["1484226000","28.3266"],["1484229600","27.15"],["1484233200","25.8114"],["1484236800","24.3325"],["1484240400","36.4067"],["1484244000","42.2212"],["1484247600","45.542"],["1484251200","39.5714"],["1484254800","37.9336"],["1484258400","52.1686"],["1484262000","99.0382"]],"avg":{"avg":"40.9511","min":"23.5204","max":"114.003"},"thresholdsForAvg":{"avg":{"at":300,"it":200,"tv":null,"lv":50,"atDecimals":0,"itDecimals":0,"tvDecimals":0,"lvDecimals":0},"min":null,"max":null},"decimals":0,"unit":"ug\/m3","unitLabel":"&micro;g\/m<sup>3<\/sup>","scaleMin":null,"scaleMax":null,"chartTooltipContent":"%y.# %ly o godz. %x"},{"label":"Krak\u00f3w, ul. Telimeny","measType":"auto","paramLabel":"Py\u0142 zawieszony PM10","paramId":"pm10","paramCode":"PM10","paramPostfix":"","aggType":"A1h","ord":7,"interval":3600,"count":24,"retroCount":2,"startTime":1484179200,"extStartTime":1484172000,"coverageRate":0.75,"isAvgValid":true,"thresholds":{"at":null,"it":null,"tv":null,"lv":null,"atDecimals":0,"itDecimals":0,"tvDecimals":0,"lvDecimals":0},"data":[["1484172000","365.176"],["1484175600","350.911"],["1484179200","319.661"],["1484182800","299.34"],["1484186400","18.1997"],["1484190000","10.7562"],["1484193600","15.8617"],["1484197200","21.872"],["1484200800","12.6351"],["1484204400","26.23"],["1484208000","30.7957"],["1484211600","32.1554"],["1484215200","23.1668"],["1484218800","25.7572"],["1484222400","28.7497"],["1484226000","25.3391"],["1484229600","16.0568"],["1484233200","26.7184"],["1484236800","20.7213"],["1484240400","28.61"],["1484244000","36.0688"],["1484247600","32.6389"],["1484251200","23.067"],["1484254800","18.4929"],["1484258400","19.62"],["1484262000","21.2965"]],"avg":{"avg":"47.2421","min":"10.7562","max":"319.661"},"thresholdsForAvg":{"avg":{"at":300,"it":200,"tv":null,"lv":50,"atDecimals":0,"itDecimals":0,"tvDecimals":0,"lvDecimals":0},"min":null,"max":null},"decimals":0,"unit":"ug\/m3","unitLabel":"&micro;g\/m<sup>3<\/sup>","scaleMin":null,"scaleMax":null,"chartTooltipContent":"%y.# %ly o godz. %x"},{"label":"Krak\u00f3w, ul. Z\u0142oty R\u00f3g","measType":"auto","paramLabel":"Py\u0142 zawieszony PM10","paramId":"pm10","paramCode":"PM10","paramPostfix":"","aggType":"A1h","ord":7,"interval":3600,"count":24,"retroCount":2,"startTime":1484179200,"extStartTime":1484172000,"coverageRate":0.75,"isAvgValid":true,"thresholds":{"at":null,"it":null,"tv":null,"lv":null,"atDecimals":0,"itDecimals":0,"tvDecimals":0,"lvDecimals":0},"data":[["1484172000","261.848"],["1484175600","266.258"],["1484179200","233.582"],["1484182800","102.045"],["1484186400","24.4184"],["1484190000","17.364"],["1484193600","19.5482"],["1484197200","20.1517"],["1484200800","21.1111"],["1484204400","23.5736"],["1484208000","26.7182"],["1484211600","26.3482"],["1484215200","26.8672"],["1484218800","29.3194"],["1484222400","25.881"],["1484226000","25.9409"],["1484229600","22.5332"],["1484233200","26.8969"],["1484236800","28.2127"],["1484240400","27.4796"],["1484244000","35.2646"],["1484247600","46.0883"],["1484251200","42.1302"],["1484254800","44.9103"],["1484258400","37.8461"],["1484262000","30.7613"]],"avg":{"avg":"40.208","min":"17.364","max":"233.582"},"thresholdsForAvg":{"avg":{"at":300,"it":200,"tv":null,"lv":50,"atDecimals":0,"itDecimals":0,"tvDecimals":0,"lvDecimals":0},"min":null,"max":null},"decimals":0,"unit":"ug\/m3","unitLabel":"&micro;g\/m<sup>3<\/sup>","scaleMin":null,"scaleMax":null,"chartTooltipContent":"%y.# %ly o godz. %x"},{"label":"Krak\u00f3w-Kurdwan\u00f3w","measType":"auto","paramLabel":"Py\u0142 zawieszony PM10","paramId":"pm10","paramCode":"PM10","paramPostfix":"","aggType":"A1h","ord":7,"interval":3600,"count":24,"retroCount":2,"startTime":1484179200,"extStartTime":1484172000,"coverageRate":0.75,"isAvgValid":true,"thresholds":{"at":null,"it":null,"tv":null,"lv":null,"atDecimals":0,"itDecimals":0,"tvDecimals":0,"lvDecimals":0},"data":[["1484172000","375.556"],["1484175600","348.99"],["1484179200","328.691"],["1484182800","91.1382"],["1484186400","17.9238"],["1484190000","13.3259"],["1484193600","17.9632"],["1484197200","13.7196"],["1484200800","23.8965"],["1484204400","33.943"],["1484208000","40.2539"],["1484211600","25.8167"],["1484215200","25.857"],["1484218800","30.1115"],["1484222400","28.3074"],["1484226000","21.4848"],["1484229600","29.1107"],["1484233200","27.8698"],["1484236800","27.5907"],["1484240400","38.8565"],["1484244000","46.5977"],["1484247600","39.275"],["1484251200","26.9457"],["1484254800","30.4736"],["1484258400","29.1345"],["1484262000","34.0299"]],"avg":{"avg":"43.4299","min":"13.3259","max":"328.691"},"thresholdsForAvg":{"avg":{"at":300,"it":200,"tv":null,"lv":50,"atDecimals":0,"itDecimals":0,"tvDecimals":0,"lvDecimals":0},"min":null,"max":null},"decimals":0,"unit":"ug\/m3","unitLabel":"&micro;g\/m<sup>3<\/sup>","scaleMin":null,"scaleMax":null,"chartTooltipContent":"%y.# %ly o godz. %x"},{"label":"Krak\u00f3w-ul. Dietla","measType":"auto","paramLabel":"Py\u0142 zawieszony PM10","paramId":"pm10","paramCode":"PM10","paramPostfix":"","aggType":"A1h","ord":7,"interval":3600,"count":24,"retroCount":2,"startTime":1484179200,"extStartTime":1484172000,"coverageRate":0.75,"isAvgValid":true,"thresholds":{"at":null,"it":null,"tv":null,"lv":null,"atDecimals":0,"itDecimals":0,"tvDecimals":0,"lvDecimals":0},"data":[["1484172000","255.42"],["1484175600","276.75"],["1484179200","259.65"],["1484182800","134.46"],["1484186400","15.867"],["1484190000","21.024"],["1484193600","16.425"],["1484197200","23.715"],["1484200800","26.01"],["1484204400","41.184"],["1484208000","36.405"],["1484211600","34.578"],["1484215200","34.479"],["1484218800","32.823"],["1484222400","37.476"],["1484226000","34.632"],["1484229600","32.229"],["1484233200","31.311"],["1484236800","34.794"],["1484240400","32.292"],["1484244000","42.246"],["1484247600","48.627"],["1484251200","57.096"],["1484254800","45.576"],["1484258400","35.838"],["1484262000","33.921"]],"avg":{"avg":"47.6107","min":"15.867","max":"259.65"},"thresholdsForAvg":{"avg":{"at":300,"it":200,"tv":null,"lv":50,"atDecimals":0,"itDecimals":0,"tvDecimals":0,"lvDecimals":0},"min":null,"max":null},"decimals":0,"unit":"ug\/m3","unitLabel":"&micro;g\/m<sup>3<\/sup>","scaleMin":null,"scaleMax":null,"chartTooltipContent":"%y.# %ly o godz. %x"},{"label":"Nowa Huta","measType":"auto","paramLabel":"Py\u0142 zawieszony PM10","paramId":"pm10","paramCode":"PM10","paramPostfix":"","aggType":"A1h","ord":7,"interval":3600,"count":24,"retroCount":2,"startTime":1484179200,"extStartTime":1484172000,"coverageRate":0.75,"isAvgValid":true,"thresholds":{"at":null,"it":null,"tv":null,"lv":null,"atDecimals":0,"itDecimals":0,"tvDecimals":0,"lvDecimals":0},"data":[["1484172000","340.384"],["1484175600","246.182"],["1484179200","263.166"],["1484182800","136.994"],["1484186400","47.6401"],["1484190000","17.1503"],["1484193600","16.1535"],["1484197200","15.885"],["1484200800","25.374"],["1484204400","25.3006"],["1484208000","30.9915"],["1484211600","28.7798"],["1484215200","27.3845"],["1484218800","27.5003"],["1484222400","29.9956"],["1484226000","22.7122"],["1484229600","23.9792"],["1484233200","24.7984"],["1484236800","23.1316"],["1484240400","20.3483"],["1484244000","35.0589"],["1484247600","41.5155"],["1484251200","37.0392"],["1484254800","34.1661"],["1484258400","25.1786"],["1484262000","32.0737"]],"avg":{"avg":"42.1799","min":"15.885","max":"263.166"},"thresholdsForAvg":{"avg":{"at":300,"it":200,"tv":null,"lv":50,"atDecimals":0,"itDecimals":0,"tvDecimals":0,"lvDecimals":0},"min":null,"max":null},"decimals":0,"unit":"ug\/m3","unitLabel":"&micro;g\/m<sup>3<\/sup>","scaleMin":null,"scaleMax":null,"chartTooltipContent":"%y.# %ly o godz. %x"}],"dateFormat":"H:00","viewType":"parameter","messageItem":null}}