{"success":true,"data":{"charts":[],"title":"Dane pomiarowe dla parametru Py\u0142 zawieszony PM10 w dniu 22.02.2018 r.","unitLabel":"&micro;g\/m<sup>3<\/sup>","series":[{"label":"Aleja Krasi\u0144skiego","measType":"auto","paramLabel":"Py\u0142 zawieszony PM10","paramId":"pm10","paramCode":"PM10","paramPostfix":"","aggType":"A1h","ord":7,"interval":3600,"count":24,"retroCount":2,"startTime":1519257600,"extStartTime":1519250400,"coverageRate":0.75,"isAvgValid":true,"thresholds":{"at":null,"it":null,"tv":null,"lv":null,"atDecimals":0,"itDecimals":0,"tvDecimals":0,"lvDecimals":0},"data":[["1519250400","137.339"],["1519254000","146.433"],["1519257600","78.1114"],["1519261200","50.9747"],["1519264800","49.4711"],["1519268400","48.3544"],["1519272000","46.3797"],["1519275600","46.0508"],["1519279200","61.8378"],["1519282800","54.6031"],["1519286400","43.9106"],["1519290000","57.4214"],["1519293600","63.5833"],["1519297200","64.5922"],["1519300800","60.673"],["1519304400","57.1706"],["1519308000","59.9511"],["1519311600","58.6269"],["1519315200","46.5197"],["1519318800","50.2239"],["1519322400","48.1928"],["1519326000","51.5325"],["1519329600","48.0522"],["1519333200","39.2519"],["1519336800","42.5539"],["1519340400","44.1325"]],"avg":{"avg":"53.0071","min":"39.2519","max":"78.1114"},"thresholdsForAvg":{"avg":{"at":300,"it":200,"tv":null,"lv":50,"atDecimals":0,"itDecimals":0,"tvDecimals":0,"lvDecimals":0},"min":null,"max":null},"decimals":0,"unit":"ug\/m3","unitLabel":"&micro;g\/m<sup>3<\/sup>","scaleMin":null,"scaleMax":null,"chartTooltipContent":"%y.# %ly o godz. %x"},{"label":"Krak\u00f3w, os. Piast\u00f3w","measType":"auto","paramLabel":"Py\u0142 zawieszony PM10","paramId":"pm10","paramCode":"PM10","paramPostfix":"","aggType":"A1h","ord":7,"interval":3600,"count":24,"retroCount":2,"startTime":1519257600,"extStartTime":1519250400,"coverageRate":0.75,"isAvgValid":true,"thresholds":{"at":null,"it":null,"tv":null,"lv":null,"atDecimals":0,"itDecimals":0,"tvDecimals":0,"lvDecimals":0},"data":[["1519250400","84.1267"],["1519254000","61.1207"],["1519257600","42.8742"],["1519261200","41.4119"],["1519264800","42.3167"],["1519268400","39.7637"],["1519272000","38.0205"],["1519275600","33.9322"],["1519279200","30.3712"],["1519282800","31.6135"],["1519286400","31.7558"],["1519290000","33.2255"],["1519293600","40.0058"],["1519297200","40.1274"],["1519300800","35.7915"],["1519304400","34.2112"],["1519308000","27.1378"],["1519311600","28.8522"],["1519318800","29.9671"],["1519322400","26.3255"],["1519326000","32.3761"],["1519329600","30.8064"],["1519333200","24.7763"],["1519336800","29.8944"],["1519340400","29.3084"]],"avg":{"avg":"33.6898","min":"24.7763","max":"42.8742"},"thresholdsForAvg":{"avg":{"at":300,"it":200,"tv":null,"lv":50,"atDecimals":0,"itDecimals":0,"tvDecimals":0,"lvDecimals":0},"min":null,"max":null},"decimals":0,"unit":"ug\/m3","unitLabel":"&micro;g\/m<sup>3<\/sup>","scaleMin":null,"scaleMax":null,"chartTooltipContent":"%y.# %ly o godz. %x"},{"label":"Krak\u00f3w, os. Wad\u00f3w","measType":"auto","paramLabel":"Py\u0142 zawieszony PM10","paramId":"pm10","paramCode":"PM10","paramPostfix":"","aggType":"A1h","ord":7,"interval":3600,"count":24,"retroCount":2,"startTime":1519257600,"extStartTime":1519250400,"coverageRate":0.75,"isAvgValid":true,"thresholds":{"at":null,"it":null,"tv":null,"lv":null,"atDecimals":0,"itDecimals":0,"tvDecimals":0,"lvDecimals":0},"data":[["1519250400","78.4687"],["1519254000","48.1574"],["1519257600","44.9214"],["1519261200","42.7244"],["1519264800","53.7533"],["1519268400","39.4578"],["1519272000","31.0474"],["1519275600","29.0352"],["1519279200","27.6399"],["1519282800","28.515"],["1519286400","22.347"],["1519290000","27.2678"],["1519293600","29.754"],["1519297200","24.5974"],["1519300800","26.1987"],["1519304400","22.334"],["1519308000","25.5098"],["1519311600","20.4688"],["1519315200","21.5298"],["1519318800","23.9622"],["1519322400","33.2114"],["1519326000","26.0888"],["1519329600","23.59"],["1519333200","30.2341"],["1519336800","34.329"],["1519340400","30.4146"]],"avg":{"avg":"29.9555","min":"20.4688","max":"53.7533"},"thresholdsForAvg":{"avg":{"at":300,"it":200,"tv":null,"lv":50,"atDecimals":0,"itDecimals":0,"tvDecimals":0,"lvDecimals":0},"min":null,"max":null},"decimals":0,"unit":"ug\/m3","unitLabel":"&micro;g\/m<sup>3<\/sup>","scaleMin":null,"scaleMax":null,"chartTooltipContent":"%y.# %ly o godz. %x"},{"label":"Krak\u00f3w, ul. Telimeny","measType":"auto","paramLabel":"Py\u0142 zawieszony PM10","paramId":"pm10","paramCode":"PM10","paramPostfix":"","aggType":"A1h","ord":7,"interval":3600,"count":24,"retroCount":2,"startTime":1519257600,"extStartTime":1519250400,"coverageRate":0.75,"isAvgValid":true,"thresholds":{"at":null,"it":null,"tv":null,"lv":null,"atDecimals":0,"itDecimals":0,"tvDecimals":0,"lvDecimals":0},"data":[["1519250400","108.791"],["1519254000","114.016"],["1519257600","92.7231"],["1519261200","55.9173"],["1519264800","50.3199"],["1519268400","51.3976"],["1519272000","46.2087"],["1519275600","38.2143"],["1519279200","37.935"],["1519282800","31.6092"],["1519286400","40.2404"],["1519290000","30.3883"],["1519293600","29.9152"],["1519297200","30.2331"],["1519300800","27.8636"],["1519304400","32.1178"],["1519308000","30.0353"],["1519311600","33.3571"],["1519318800","31.3325"],["1519322400","31.6381"],["1519326000","30.2146"],["1519329600","25.472"],["1519333200","30.904"],["1519336800","32.6461"],["1519340400","37.4736"]],"avg":{"avg":"38.1807","min":"25.472","max":"92.7231"},"thresholdsForAvg":{"avg":{"at":300,"it":200,"tv":null,"lv":50,"atDecimals":0,"itDecimals":0,"tvDecimals":0,"lvDecimals":0},"min":null,"max":null},"decimals":0,"unit":"ug\/m3","unitLabel":"&micro;g\/m<sup>3<\/sup>","scaleMin":null,"scaleMax":null,"chartTooltipContent":"%y.# %ly o godz. %x"},{"label":"Krak\u00f3w, ul. Z\u0142oty R\u00f3g","measType":"auto","paramLabel":"Py\u0142 zawieszony PM10","paramId":"pm10","paramCode":"PM10","paramPostfix":"","aggType":"A1h","ord":7,"interval":3600,"count":24,"retroCount":2,"startTime":1519257600,"extStartTime":1519250400,"coverageRate":0.75,"isAvgValid":true,"thresholds":{"at":null,"it":null,"tv":null,"lv":null,"atDecimals":0,"itDecimals":0,"tvDecimals":0,"lvDecimals":0},"data":[["1519250400","93.9251"],["1519254000","116.401"],["1519257600","57.3468"],["1519261200","48.7967"],["1519264800","48.2822"],["1519268400","44.8106"],["1519272000","44.1846"],["1519275600","44.7782"],["1519279200","36.018"],["1519282800","38.441"],["1519286400","35.7218"],["1519290000","32.577"],["1519293600","41.4982"],["1519297200","35.7605"],["1519300800","41.4317"],["1519304400","35.3093"],["1519308000","29.8544"],["1519311600","31.0603"],["1519318800","30.1069"],["1519322400","32.8894"],["1519326000","29.5818"],["1519329600","32.5992"],["1519333200","22.039"],["1519336800","30.4379"],["1519340400","31.1518"]],"avg":{"avg":"37.1599","min":"22.039","max":"57.3468"},"thresholdsForAvg":{"avg":{"at":300,"it":200,"tv":null,"lv":50,"atDecimals":0,"itDecimals":0,"tvDecimals":0,"lvDecimals":0},"min":null,"max":null},"decimals":0,"unit":"ug\/m3","unitLabel":"&micro;g\/m<sup>3<\/sup>","scaleMin":null,"scaleMax":null,"chartTooltipContent":"%y.# %ly o godz. %x"},{"label":"Krak\u00f3w-Kurdwan\u00f3w","measType":"auto","paramLabel":"Py\u0142 zawieszony PM10","paramId":"pm10","paramCode":"PM10","paramPostfix":"","aggType":"A1h","ord":7,"interval":3600,"count":24,"retroCount":2,"startTime":1519257600,"extStartTime":1519250400,"coverageRate":0.75,"isAvgValid":true,"thresholds":{"at":null,"it":null,"tv":null,"lv":null,"atDecimals":0,"itDecimals":0,"tvDecimals":0,"lvDecimals":0},"data":[["1519250400","117.753"],["1519254000","103.542"],["1519257600","101.292"],["1519261200","34.8881"],["1519264800","43.8026"],["1519268400","41.0141"],["1519272000","43.9505"],["1519275600","36.716"],["1519279200","31.2439"],["1519282800","27.1784"],["1519286400","31.3267"],["1519290000","27.5437"],["1519293600","37.528"],["1519297200","25.27"],["1519300800","28.8657"],["1519304400","31.3871"],["1519308000","29.8265"],["1519311600","25.9916"],["1519315200","32.8131"],["1519318800","30.2185"],["1519322400","33.3692"],["1519326000","22.2934"],["1519329600","24.8274"],["1519333200","26.6625"],["1519336800","30.9154"],["1519340400","36.4229"]],"avg":{"avg":"34.8061","min":"22.2934","max":"101.292"},"thresholdsForAvg":{"avg":{"at":300,"it":200,"tv":null,"lv":50,"atDecimals":0,"itDecimals":0,"tvDecimals":0,"lvDecimals":0},"min":null,"max":null},"decimals":0,"unit":"ug\/m3","unitLabel":"&micro;g\/m<sup>3<\/sup>","scaleMin":null,"scaleMax":null,"chartTooltipContent":"%y.# %ly o godz. %x"},{"label":"Krak\u00f3w-ul. Dietla","measType":"auto","paramLabel":"Py\u0142 zawieszony PM10","paramId":"pm10","paramCode":"PM10","paramPostfix":"","aggType":"A1h","ord":7,"interval":3600,"count":24,"retroCount":2,"startTime":1519257600,"extStartTime":1519250400,"coverageRate":0.75,"isAvgValid":true,"thresholds":{"at":null,"it":null,"tv":null,"lv":null,"atDecimals":0,"itDecimals":0,"tvDecimals":0,"lvDecimals":0},"data":[["1519250400","105.03"],["1519254000","110.252"],["1519257600","42.4594"],["1519261200","47.2692"],["1519264800","40.1922"],["1519268400","44.0669"],["1519272000","38.4562"],["1519275600","40.0301"],["1519279200","35.6974"],["1519282800","40.3729"],["1519286400","37.332"],["1519290000","35.0397"],["1519293600","38.8583"],["1519297200","52.1159"],["1519300800","57.6611"],["1519304400","49.481"],["1519308000","52.5495"],["1519311600","48.1638"],["1519315200","41.5048"],["1519318800","44.3371"],["1519322400","47.0244"],["1519326000","41.1602"],["1519329600","47.4456"],["1519333200","31.1271"],["1519336800","33.0548"],["1519340400","27.317"]],"avg":{"avg":"42.1965","min":"27.317","max":"57.6611"},"thresholdsForAvg":{"avg":{"at":300,"it":200,"tv":null,"lv":50,"atDecimals":0,"itDecimals":0,"tvDecimals":0,"lvDecimals":0},"min":null,"max":null},"decimals":0,"unit":"ug\/m3","unitLabel":"&micro;g\/m<sup>3<\/sup>","scaleMin":null,"scaleMax":null,"chartTooltipContent":"%y.# %ly o godz. %x"},{"label":"Nowa Huta","measType":"auto","paramLabel":"Py\u0142 zawieszony PM10","paramId":"pm10","paramCode":"PM10","paramPostfix":"","aggType":"A1h","ord":7,"interval":3600,"count":24,"retroCount":2,"startTime":1519257600,"extStartTime":1519250400,"coverageRate":0.75,"isAvgValid":true,"thresholds":{"at":null,"it":null,"tv":null,"lv":null,"atDecimals":0,"itDecimals":0,"tvDecimals":0,"lvDecimals":0},"data":[["1519250400","89.5948"],["1519254000","75.0289"],["1519257600","53.3263"],["1519261200","46.8113"],["1519264800","52.3135"],["1519268400","44.6597"],["1519272000","43.8021"],["1519275600","44.5209"],["1519279200","34.3183"],["1519282800","40.2867"],["1519286400","39.7895"],["1519290000","43.1001"],["1519293600","37.6018"],["1519297200","42.6469"],["1519300800","32.8931"],["1519304400","28.3945"],["1519308000","32.9975"],["1519311600","26.0175"],["1519315200","27.7432"],["1519318800","38.4939"],["1519322400","33.6585"],["1519326000","48.78"],["1519329600","40.8651"],["1519333200","32.4132"],["1519336800","39.8845"],["1519340400","41.6889"]],"avg":{"avg":"39.4586","min":"26.0175","max":"53.3263"},"thresholdsForAvg":{"avg":{"at":300,"it":200,"tv":null,"lv":50,"atDecimals":0,"itDecimals":0,"tvDecimals":0,"lvDecimals":0},"min":null,"max":null},"decimals":0,"unit":"ug\/m3","unitLabel":"&micro;g\/m<sup>3<\/sup>","scaleMin":null,"scaleMax":null,"chartTooltipContent":"%y.# %ly o godz. %x"}],"dateFormat":"H:00","viewType":"parameter","messageItem":null}}