{"success":true,"data":{"charts":[],"title":"Dane pomiarowe dla parametru Py\u0142 zawieszony PM10 w dniu 28.02.2018 r.","unitLabel":"&micro;g\/m<sup>3<\/sup>","series":[{"label":"Aleja Krasi\u0144skiego","measType":"auto","paramLabel":"Py\u0142 zawieszony PM10","paramId":"pm10","paramCode":"PM10","paramPostfix":"","aggType":"A1h","ord":7,"interval":3600,"count":24,"retroCount":2,"startTime":1519776000,"extStartTime":1519768800,"coverageRate":0.75,"isAvgValid":true,"thresholds":{"at":null,"it":null,"tv":null,"lv":null,"atDecimals":0,"itDecimals":0,"tvDecimals":0,"lvDecimals":0},"data":[["1519768800","34.4456"],["1519772400","34.1444"],["1519776000","31.9028"],["1519779600","30.3169"],["1519783200","28.7772"],["1519786800","27.3883"],["1519790400","26.5825"],["1519794000","29.6831"],["1519797600","30.2381"],["1519801200","34.7731"],["1519804800","34.2406"],["1519808400","38.145"],["1519812000","45.5992"],["1519815600","37.6119"],["1519819200","38.6814"],["1519822800","33.0667"],["1519826400","36.6456"],["1519830000","40.8542"],["1519833600","41.5633"],["1519837200","44.8475"],["1519840800","53.9533"],["1519844400","51.7989"],["1519848000","44.1389"],["1519851600","53.1606"],["1519855200","51.0867"],["1519858800","70.5853"]],"avg":{"avg":"39.8184","min":"26.5825","max":"70.5853"},"thresholdsForAvg":{"avg":{"at":300,"it":200,"tv":null,"lv":50,"atDecimals":0,"itDecimals":0,"tvDecimals":0,"lvDecimals":0},"min":null,"max":null},"decimals":0,"unit":"ug\/m3","unitLabel":"&micro;g\/m<sup>3<\/sup>","scaleMin":null,"scaleMax":null,"chartTooltipContent":"%y.# %ly o godz. %x"},{"label":"Krak\u00f3w, os. Piast\u00f3w","measType":"auto","paramLabel":"Py\u0142 zawieszony PM10","paramId":"pm10","paramCode":"PM10","paramPostfix":"","aggType":"A1h","ord":7,"interval":3600,"count":24,"retroCount":2,"startTime":1519776000,"extStartTime":1519768800,"coverageRate":0.75,"isAvgValid":true,"thresholds":{"at":null,"it":null,"tv":null,"lv":null,"atDecimals":0,"itDecimals":0,"tvDecimals":0,"lvDecimals":0},"data":[["1519768800","32.4195"],["1519772400","26.2241"],["1519776000","29.0207"],["1519779600","22.3375"],["1519783200","18.8323"],["1519786800","21.9167"],["1519790400","24.6715"],["1519794000","17.8894"],["1519797600","24.0796"],["1519801200","29.4164"],["1519804800","27.4167"],["1519808400","25.9807"],["1519812000","28.3438"],["1519815600","23.1847"],["1519819200","22.4331"],["1519822800","27.0473"],["1519826400","30.1078"],["1519830000","35.4303"],["1519833600","35.1225"],["1519837200","36.1097"],["1519840800","55.0228"],["1519844400","38.9728"],["1519848000","54.2749"],["1519851600","54.5049"],["1519855200","43.1746"],["1519858800","52.3385"]],"avg":{"avg":"32.4012","min":"17.8894","max":"55.0228"},"thresholdsForAvg":{"avg":{"at":300,"it":200,"tv":null,"lv":50,"atDecimals":0,"itDecimals":0,"tvDecimals":0,"lvDecimals":0},"min":null,"max":null},"decimals":0,"unit":"ug\/m3","unitLabel":"&micro;g\/m<sup>3<\/sup>","scaleMin":null,"scaleMax":null,"chartTooltipContent":"%y.# %ly o godz. %x"},{"label":"Krak\u00f3w, os. Wad\u00f3w","measType":"auto","paramLabel":"Py\u0142 zawieszony PM10","paramId":"pm10","paramCode":"PM10","paramPostfix":"","aggType":"A1h","ord":7,"interval":3600,"count":24,"retroCount":2,"startTime":1519776000,"extStartTime":1519768800,"coverageRate":0.75,"isAvgValid":true,"thresholds":{"at":null,"it":null,"tv":null,"lv":null,"atDecimals":0,"itDecimals":0,"tvDecimals":0,"lvDecimals":0},"data":[["1519768800","31.1222"],["1519772400","36.0468"],["1519776000","33.7333"],["1519779600","23.4212"],["1519783200","44.3777"],["1519786800","23.0572"],["1519790400","30.8251"],["1519794000","27.8273"],["1519797600","24.7897"],["1519801200","25.2199"],["1519804800","32.8664"],["1519808400","27.6152"],["1519812000","25.0569"],["1519815600","27.6676"],["1519819200","22.6263"],["1519822800","20.9569"],["1519826400","24.1169"],["1519830000","21.577"],["1519833600","30.8993"],["1519837200","40.5205"],["1519840800","30.7087"],["1519844400","41.876"],["1519848000","46.6904"],["1519851600","51.5723"],["1519855200","51.4508"],["1519858800","47.013"]],"avg":{"avg":"32.3527","min":"20.9569","max":"51.5723"},"thresholdsForAvg":{"avg":{"at":300,"it":200,"tv":null,"lv":50,"atDecimals":0,"itDecimals":0,"tvDecimals":0,"lvDecimals":0},"min":null,"max":null},"decimals":0,"unit":"ug\/m3","unitLabel":"&micro;g\/m<sup>3<\/sup>","scaleMin":null,"scaleMax":null,"chartTooltipContent":"%y.# %ly o godz. %x"},{"label":"Krak\u00f3w, ul. Telimeny","measType":"auto","paramLabel":"Py\u0142 zawieszony PM10","paramId":"pm10","paramCode":"PM10","paramPostfix":"","aggType":"A1h","ord":7,"interval":3600,"count":24,"retroCount":2,"startTime":1519776000,"extStartTime":1519768800,"coverageRate":0.75,"isAvgValid":true,"thresholds":{"at":null,"it":null,"tv":null,"lv":null,"atDecimals":0,"itDecimals":0,"tvDecimals":0,"lvDecimals":0},"data":[["1519768800","34.9029"],["1519772400","33.9179"],["1519776000","31.7982"],["1519779600","31.0055"],["1519783200","31.2171"],["1519786800","32.6511"],["1519790400","31.3205"],["1519794000","26.1465"],["1519797600","29.5965"],["1519801200","41.3323"],["1519804800","32.0906"],["1519808400","37.693"],["1519812000","27.3619"],["1519815600","25.8893"],["1519819200","34.1951"],["1519822800","30.1545"],["1519826400","34.1904"],["1519830000","29.4017"],["1519833600","37.0609"],["1519837200","41.5573"],["1519840800","44.1232"],["1519844400","43.5252"],["1519848000","56.4025"],["1519851600","50.9255"],["1519855200","64.4232"],["1519858800","78.0957"]],"avg":{"avg":"38.4232","min":"25.8893","max":"78.0957"},"thresholdsForAvg":{"avg":{"at":300,"it":200,"tv":null,"lv":50,"atDecimals":0,"itDecimals":0,"tvDecimals":0,"lvDecimals":0},"min":null,"max":null},"decimals":0,"unit":"ug\/m3","unitLabel":"&micro;g\/m<sup>3<\/sup>","scaleMin":null,"scaleMax":null,"chartTooltipContent":"%y.# %ly o godz. %x"},{"label":"Krak\u00f3w, ul. Z\u0142oty R\u00f3g","measType":"auto","paramLabel":"Py\u0142 zawieszony PM10","paramId":"pm10","paramCode":"PM10","paramPostfix":"","aggType":"A1h","ord":7,"interval":3600,"count":24,"retroCount":2,"startTime":1519776000,"extStartTime":1519768800,"coverageRate":0.75,"isAvgValid":true,"thresholds":{"at":null,"it":null,"tv":null,"lv":null,"atDecimals":0,"itDecimals":0,"tvDecimals":0,"lvDecimals":0},"data":[["1519768800","36.8557"],["1519772400","32.8811"],["1519776000","32.8877"],["1519779600","25.6214"],["1519783200","37.6679"],["1519786800","40.6615"],["1519790400","32.8207"],["1519794000","44.1234"],["1519797600","39.7562"],["1519801200","47.0968"],["1519804800","39.009"],["1519808400","39.713"],["1519812000","38.0523"],["1519815600","35.9058"],["1519819200","31.8567"],["1519822800","33.4953"],["1519826400","42.2109"],["1519830000","39.5176"],["1519833600","42.8333"],["1519837200","47.4743"],["1519840800","61.929"],["1519844400","57.6372"],["1519848000","46.4174"],["1519851600","57.6156"],["1519855200","57.0387"],["1519858800","61.0528"]],"avg":{"avg":"43.0164","min":"25.6214","max":"61.929"},"thresholdsForAvg":{"avg":{"at":300,"it":200,"tv":null,"lv":50,"atDecimals":0,"itDecimals":0,"tvDecimals":0,"lvDecimals":0},"min":null,"max":null},"decimals":0,"unit":"ug\/m3","unitLabel":"&micro;g\/m<sup>3<\/sup>","scaleMin":null,"scaleMax":null,"chartTooltipContent":"%y.# %ly o godz. %x"},{"label":"Krak\u00f3w-Kurdwan\u00f3w","measType":"auto","paramLabel":"Py\u0142 zawieszony PM10","paramId":"pm10","paramCode":"PM10","paramPostfix":"","aggType":"A1h","ord":7,"interval":3600,"count":24,"retroCount":2,"startTime":1519776000,"extStartTime":1519768800,"coverageRate":0.75,"isAvgValid":true,"thresholds":{"at":null,"it":null,"tv":null,"lv":null,"atDecimals":0,"itDecimals":0,"tvDecimals":0,"lvDecimals":0},"data":[["1519768800","47.2163"],["1519772400","40.5136"],["1519776000","41.1496"],["1519779600","44.8601"],["1519783200","42.4144"],["1519786800","39.9879"],["1519790400","35.3364"],["1519794000","44.2992"],["1519797600","43.7507"],["1519801200","42.1595"],["1519804800","43.7123"],["1519808400","44.8942"],["1519812000","37.6718"],["1519815600","38.1667"],["1519819200","45.0489"],["1519822800","38.2803"],["1519826400","35.1509"],["1519830000","44.4329"],["1519833600","44.8753"],["1519837200","47.2347"],["1519840800","57.0254"],["1519844400","63.0361"],["1519848000","56.397"],["1519851600","80.0916"],["1519855200","102.312"],["1519858800","153.738"]],"avg":{"avg":"52.7511","min":"35.1509","max":"153.738"},"thresholdsForAvg":{"avg":{"at":300,"it":200,"tv":null,"lv":50,"atDecimals":0,"itDecimals":0,"tvDecimals":0,"lvDecimals":0},"min":null,"max":null},"decimals":0,"unit":"ug\/m3","unitLabel":"&micro;g\/m<sup>3<\/sup>","scaleMin":null,"scaleMax":null,"chartTooltipContent":"%y.# %ly o godz. %x"},{"label":"Krak\u00f3w-ul. Dietla","measType":"auto","paramLabel":"Py\u0142 zawieszony PM10","paramId":"pm10","paramCode":"PM10","paramPostfix":"","aggType":"A1h","ord":7,"interval":3600,"count":24,"retroCount":2,"startTime":1519776000,"extStartTime":1519768800,"coverageRate":0.75,"isAvgValid":true,"thresholds":{"at":null,"it":null,"tv":null,"lv":null,"atDecimals":0,"itDecimals":0,"tvDecimals":0,"lvDecimals":0},"data":[["1519768800","29.5567"],["1519772400","27.5081"],["1519776000","28.9542"],["1519779600","28.9359"],["1519783200","25.23"],["1519786800","22.3409"],["1519790400","23.4661"],["1519794000","26.8863"],["1519797600","25.967"],["1519801200","26.3881"],["1519804800","31.1518"],["1519808400","27.4371"],["1519812000","32.106"],["1519815600","30.3142"],["1519819200","29.0763"],["1519822800","26.9966"],["1519826400","33.5623"],["1519830000","34.7987"],["1519833600","34.1506"],["1519837200","38.8036"],["1519840800","42.7442"],["1519844400","46.1301"],["1519848000","39.8631"],["1519851600","54.0435"],["1519855200","48.9695"],["1519858800","57.3375"]],"avg":{"avg":"33.9856","min":"22.3409","max":"57.3375"},"thresholdsForAvg":{"avg":{"at":300,"it":200,"tv":null,"lv":50,"atDecimals":0,"itDecimals":0,"tvDecimals":0,"lvDecimals":0},"min":null,"max":null},"decimals":0,"unit":"ug\/m3","unitLabel":"&micro;g\/m<sup>3<\/sup>","scaleMin":null,"scaleMax":null,"chartTooltipContent":"%y.# %ly o godz. %x"},{"label":"Nowa Huta","measType":"auto","paramLabel":"Py\u0142 zawieszony PM10","paramId":"pm10","paramCode":"PM10","paramPostfix":"","aggType":"A1h","ord":7,"interval":3600,"count":24,"retroCount":2,"startTime":1519776000,"extStartTime":1519768800,"coverageRate":0.75,"isAvgValid":true,"thresholds":{"at":null,"it":null,"tv":null,"lv":null,"atDecimals":0,"itDecimals":0,"tvDecimals":0,"lvDecimals":0},"data":[["1519768800","42.739"],["1519772400","34.7596"],["1519776000","38.9914"],["1519779600","40.2347"],["1519783200","27.0921"],["1519786800","32.082"],["1519790400","28.8488"],["1519794000","34.4696"],["1519797600","30.7738"],["1519801200","37.0893"],["1519804800","37.7568"],["1519808400","34.8887"],["1519812000","32.451"],["1519815600","29.0308"],["1519819200","28.6393"],["1519822800","27.0594"],["1519826400","26.5354"],["1519830000","36.7049"],["1519833600","36.5995"],["1519837200","40.1444"],["1519840800","44.563"],["1519844400","45.8127"],["1519848000","45.4261"],["1519851600","56.2186"],["1519855200","64.5431"],["1519858800","78.0983"]],"avg":{"avg":"38.9189","min":"26.5354","max":"78.0983"},"thresholdsForAvg":{"avg":{"at":300,"it":200,"tv":null,"lv":50,"atDecimals":0,"itDecimals":0,"tvDecimals":0,"lvDecimals":0},"min":null,"max":null},"decimals":0,"unit":"ug\/m3","unitLabel":"&micro;g\/m<sup>3<\/sup>","scaleMin":null,"scaleMax":null,"chartTooltipContent":"%y.# %ly o godz. %x"}],"dateFormat":"H:00","viewType":"parameter","messageItem":null}}